keras_gym/__init__.py
keras_gym/base/__init__.py
keras_gym/base/errors.py
keras_gym/base/mixins.py
keras_gym/base/patches.py
keras_gym/caching/__init__.py
keras_gym/caching/experience_replay.py
keras_gym/caching/short_term.py
keras_gym/caching/test_experience_replay.py
keras_gym/caching/test_short_term.py
keras_gym/core/__init__.py
keras_gym/core/actor_critic.py
keras_gym/core/base.py
keras_gym/core/function_approximator.py
keras_gym/core/policy_categorical.py
keras_gym/core/policy_normal.py
keras_gym/core/test_sync_target_model.py
keras_gym/core/value_q.py
keras_gym/core/value_v.py
keras_gym/core/predefined/__init__.py
keras_gym/core/predefined/atari.py
keras_gym/core/predefined/connect_four.py
keras_gym/core/predefined/linear.py
keras_gym/core/predefined/mixins.py
keras_gym/envs/__init__.py
keras_gym/envs/self_play.py
keras_gym/losses/__init__.py
keras_gym/losses/base.py
keras_gym/losses/value_based.py
keras_gym/planning/__init__.py
keras_gym/planning/monte_carlo_tree_search.py
keras_gym/policies/__init__.py
keras_gym/policies/base.py
keras_gym/policies/special.py
keras_gym/policies/test_special.py
keras_gym/policies/value_based.py
keras_gym/proba_dists/__init__.py
keras_gym/proba_dists/base.py
keras_gym/proba_dists/categorical.py
keras_gym/proba_dists/normal.py
keras_gym/proba_dists/test_categorical.py
keras_gym/proba_dists/test_normal.py
keras_gym/utils/__init__.py
keras_gym/utils/array.py
keras_gym/utils/misc.py
keras_gym/utils/tensor.py
keras_gym/utils/test_array.py
keras_gym/utils/test_tensor.py
keras_gym/wrappers/__init__.py
keras_gym/wrappers/box_spaces.py
keras_gym/wrappers/default.py
keras_gym/wrappers/monitors.py
keras_gym/wrappers/test_video.py
keras_gym/wrappers/video.py
keras_gym-0.2.17.dist-info/LICENSE
keras_gym-0.2.17.dist-info/METADATA
keras_gym-0.2.17.dist-info/WHEEL
keras_gym-0.2.17.dist-info/top_level.txt
keras_gym-0.2.17.dist-info/zip-safe
keras_gym-0.2.17.dist-info/RECORD
